README.md
README.rst
setup.py
jsax/__init__.py
jsax/agg.py
jsax/aggmem.c
jsax/aggmem.pyx
jsax/comp.py
jsax/compmem.c
jsax/compmem.pyx
jsax/fkmns.py
jsax/inverset.py
jsax/inversetc.c
jsax/inversetc.pyx
jsax/jsax.py
jsax/loadData.py
jsax/preprocessing.py
jsax.egg-info/PKG-INFO
jsax.egg-info/SOURCES.txt
jsax.egg-info/dependency_links.txt
jsax.egg-info/requires.txt
jsax.egg-info/top_level.txt
jsax/__pycache__/__init__.cpython-39.pyc
jsax/__pycache__/agg.cpython-39.pyc
jsax/__pycache__/comp.cpython-39.pyc
jsax/__pycache__/fkmns.cpython-39.pyc
jsax/__pycache__/inverset.cpython-39.pyc
jsax/__pycache__/pabba.cpython-39.pyc
jsax/data/__init__.py
jsax/data/beef_test.npy
jsax/data/beef_train.npy